lijnpy/__init__.py
lijnpy/_rest_adapter.py
lijnpy/enums.py
lijnpy/kods_client_v1.py
lijnpy/models.py
lijnpy-1.0.0.dist-info/METADATA
lijnpy-1.0.0.dist-info/WHEEL
lijnpy-1.0.0.dist-info/RECORD
