Metadata-Version: 2.1
Name: lijnpy
Version: 1.0.0
Summary: 
License: MIT
Author: Ilias Bachiri
Author-email: ilias.bachiri@gmail.com
Requires-Python: >=3.12,<4.0
Classifier: License :: OSI Approved :: MIT License
Classifier: Programming Language :: Python :: 3
Classifier: Programming Language :: Python :: 3.12
Requires-Dist: aiohttp (>=3.9.5,<4.0.0)
Requires-Dist: pydantic (>=2.6.3,<3.0.0)
Requires-Dist: pydantic-extra-types (>=2.6.0,<3.0.0)
Requires-Dist: requests (>=2.31.0,<3.0.0)
